envtext/__init__.py
envtext/requirements.txt
envtext/data/__init__.py
envtext/data/data_collator.py
envtext/data/dataset_utils.py
envtext/data/load_files.py
envtext/data/process_test_dataset.py
envtext/data/process_train_dataset.py
envtext/data/utils.py
envtext/examples/tf_idf_cls.py
envtext/examples/train_phrase_mask_bert.py
envtext/examples/word_discovery.py
envtext/files/__init__.py
envtext/files/datasets/CLS_IsClimate.json
envtext/files/datasets/CLUENER.json
envtext/files/datasets/SA_Intensity.json
envtext/files/pretrained_models/word2vec64
envtext/files/vocab/bert_vocab.txt
envtext/files/vocab/entity.txt
envtext/files/vocab/entity.vocab
envtext/files/vocab/env_vocab.jieba.txt
envtext/files/vocab/onehot_vocab.txt
envtext/files/vocab/stop_words.txt
envtext/models/__init__.py
envtext/models/albert_cls.py
envtext/models/albert_multichoice.py
envtext/models/albert_ner.py
envtext/models/bert2vec.py
envtext/models/bert_base.py
envtext/models/bert_cls.py
envtext/models/bert_gp.py
envtext/models/bert_mlm.py
envtext/models/bert_multichoice.py
envtext/models/bert_ner.py
envtext/models/bert_relation.py
envtext/models/bert_sa.py
envtext/models/bert_span.py
envtext/models/bert_triple.py
envtext/models/cls_base.py
envtext/models/cnn_cls.py
envtext/models/cnn_discourse_cls.py
envtext/models/dp_base.py
envtext/models/gp_base.py
envtext/models/mc_base.py
envtext/models/model_base.py
envtext/models/ner_base.py
envtext/models/relation_base.py
envtext/models/rnn_base.py
envtext/models/rnn_cls.py
envtext/models/rnn_multichoice.py
envtext/models/rnn_ner.py
envtext/models/rnn_sa.py
envtext/models/sa_base.py
envtext/models/sim2vec.py
envtext/models/span_base.py
envtext/models/tfidf_cls.py
envtext/models/triple_base.py
envtext/models/word2vec.py
envtext/models/__pycache__/word2vec.cpython-38.pyc
envtext/models/__pycache__/word2vec.cpython-39.pyc
envtext/tokenizers/__init__.py
envtext/tokenizers/onehot_tokenizer.py
envtext/tokenizers/tf_idf_tokenizer.py
envtext-0.1.4.dist-info/LICENSE
envtext-0.1.4.dist-info/METADATA
envtext-0.1.4.dist-info/WHEEL
envtext-0.1.4.dist-info/top_level.txt
envtext-0.1.4.dist-info/RECORD
