Metadata-Version: 2.1
Name: envtext
Version: 0.1.4
Summary: envtext for Chinese texts analysis in Environment domain
Home-page: https://github.com/celtics1863/envtext
Author: Bi Huaibin
Author-email: bi.huaibin@foxmail.com
License: UNKNOWN
Project-URL: Bug Tracker, https://github.com/celtics1863/envtext/issues
Keywords: NLP,bert,Chinese,LSTM,RNN,domain text analysis
Platform: UNKNOWN
Classifier: Programming Language :: Python :: 3
Classifier: License :: OSI Approved :: Apache Software License
Classifier: Operating System :: OS Independent
Classifier: Programming Language :: Python :: 3
Classifier: Programming Language :: Python :: 3.6
Classifier: Programming Language :: Python :: 3.7
Classifier: Programming Language :: Python :: 3.8
Classifier: Programming Language :: Python :: 3.9
Classifier: Topic :: Text Processing
Classifier: Topic :: Text Processing :: Indexing
Classifier: Topic :: Text Processing :: Linguistic
Classifier: Topic :: Scientific/Engineering :: Artificial Intelligence
Requires-Python: >=3.6
License-File: LICENSE
Requires-Dist: jieba
Requires-Dist: datasets
Requires-Dist: gensim
Requires-Dist: tqdm
Requires-Dist: numpy
Requires-Dist: pytorch-crf
Requires-Dist: pandas
Requires-Dist: torch
Requires-Dist: transformers
Requires-Dist: einops
Requires-Dist: palettable
